cache_simulator-2.0.2.dist-info/licenses/LICENSE.txt
cachesimulator/__main__.py
cachesimulator/bin_addr.py
cachesimulator/cache.py
cachesimulator/reference.py
cachesimulator/simulator.py
cachesimulator/table.py
cachesimulator/word_addr.py
cache_simulator-2.0.2.dist-info/METADATA
cache_simulator-2.0.2.dist-info/WHEEL
cache_simulator-2.0.2.dist-info/entry_points.txt
cache_simulator-2.0.2.dist-info/top_level.txt
cache_simulator-2.0.2.dist-info/RECORD
