Metadata-Version: 2.4
Name: cache-simulator
Version: 2.0.2
Summary: A processor cache simulator for the MIPS ISA
Author-email: Caleb Evans <caleb@calebevans.me>
Maintainer-email: Caleb Evans <caleb@calebevans.me>
License-Expression: MIT
Project-URL: homepage, https://github.com/caleb531/cache-simulator
Project-URL: documentation, https://github.com/caleb531/cache-simulator#readme
Project-URL: repository, https://github.com/caleb531/cache-simulator
Project-URL: changelog, https://github.com/caleb531/cache-simulator/releases
Keywords: mips,processor,cache,simulator,architecture
Requires-Python: >=3.9
License-File: LICENSE.txt
Dynamic: license-file
